vis/__init__.py
vis/ani.py
vis/indicator.py
vis/layout.py
vis/ntype.py
vis/plot.py
vis/version.py
vis-0.0.5.dist-info/METADATA
vis-0.0.5.dist-info/RECORD
vis-0.0.5.dist-info/WHEEL
vis-0.0.5.dist-info/top_level.txt
