Metadata-Version: 2.1
Name: vis
Version: 0.0.5
Summary: Simple Visualization Tools
Home-page: https://github.com/jam31118/vis
Author: sahn
Author-email: jam31118@gmail.com
License: GPLv3
Keywords: visualization,physics,animation,plot
Platform: UNKNOWN
Classifier: Topic :: Scientific/Engineering :: Visualization
Classifier: License :: OSI Approved :: GNU Affero General Public License v3
Classifier: Programming Language :: Python :: 3.5
Classifier: Programming Language :: Python :: 3.6
Requires-Dist: numpy
Requires-Dist: matplotlib
